{
  "product_name": "Heltec V2 SX1276 (OpenRC AeroLink)",
  "lua_name": "Heltec V2",
  "layout_version": 1,
  "serial_rx": 17,
  "serial_tx": 23,
  "serial_baudrate": 400000,
  "radio_busy": -1,
  "radio_dio0": 26,
  "radio_dio1": 35,
  "radio_miso": 19,
  "radio_mosi": 27,
  "radio_nss": 18,
  "radio_rst": 14,
  "radio_sck": 5,
  "radio_rxen": -1,
  "radio_txen": -1,
  "power_min": 0,
  "power_high": 2,
  "power_max": 3,
  "power_default": 1,
  "power_control": 0,
  "power_values": [-9, -6, 0, 14],
  "screen_type": 1,
  "screen_sck": 15,
  "screen_sda": 4,
  "screen_reversed": 0,
  "screen_rst": 16,
  "button": 0,
  "button_led_index": 0,
  "led": 25,
  "led_red": -1,
  "led_green": -1,
  "led_blue": -1,
  "led_red_invert": false,
  "led_green_invert": false,
  "led_blue_invert": false
}
